rdmhelper/__init__.py
rdmhelper/keeper.py
rdmhelper/nextcloud.py
rdmhelper-1.0.2.dist-info/METADATA
rdmhelper-1.0.2.dist-info/WHEEL
rdmhelper-1.0.2.dist-info/licenses/AUTHORS.rst
rdmhelper-1.0.2.dist-info/licenses/LICENSE.md
rdmhelper-1.0.2.dist-info/RECORD
