Metadata-Version: 2.1
Name: rdmhelper
Version: 1.0.2
Summary: Manage research data in cloud services.
Project-URL: Project Homepage, https://modelsen.mpiwg-berlin.mpg.de
Project-URL: Homepage, https://gitlab.gwdg.de/modelsen/mpg-cloud
Project-URL: Bug Tracker, https://gitlab.gwdg.de/modelsen/mpg-cloud/-/issues
Author: Hannes Benne
Author-email: Malte Vogl <vogl@gea.mpg.de>
License-File: AUTHORS.rst
License-File: LICENSE.md
Classifier: License :: OSI Approved :: MIT License
Classifier: Operating System :: OS Independent
Classifier: Programming Language :: Python :: 3
Requires-Python: >=3.8
Requires-Dist: beautifulsoup4
Requires-Dist: lxml
Requires-Dist: requests
Requires-Dist: requests-toolbelt
Provides-Extra: dev
Requires-Dist: python-dotenv; extra == 'dev'
Requires-Dist: sphinx; extra == 'dev'
Requires-Dist: tox; extra == 'dev'
Requires-Dist: twine; extra == 'dev'
